vielinko_dist/Binomialdistribution.py
vielinko_dist/Gaussiandistribution.py
vielinko_dist/Generaldistribution.py
vielinko_dist/__init__.py
vielinko_distritutions-0.1b0.dist-info/DESCRIPTION.rst
vielinko_distritutions-0.1b0.dist-info/METADATA
vielinko_distritutions-0.1b0.dist-info/RECORD
vielinko_distritutions-0.1b0.dist-info/WHEEL
vielinko_distritutions-0.1b0.dist-info/metadata.json
vielinko_distritutions-0.1b0.dist-info/top_level.txt
