Metadata-Version: 2.0
Name: vielinko-distritutions
Version: 0.1b0
Summary: Gaussian and Binomial distributions
Home-page: UNKNOWN
Author: Victor Lutin
Author-email: victor.lutin@gmail.com
License: UNKNOWN
Platform: UNKNOWN
